README.md
setup.cfg
setup.py
src/external_requests/__init__.py
src/external_requests/exceptions.py
src/external_requests/external_response.py
src/external_requests/request_methods.py
src/external_requests/serialization_schema.py
src/external_requests.egg-info/PKG-INFO
src/external_requests.egg-info/SOURCES.txt
src/external_requests.egg-info/dependency_links.txt
src/external_requests.egg-info/requires.txt
src/external_requests.egg-info/top_level.txt
src/external_requests/base_requests/__init__.py
src/external_requests/base_requests/external_request.py
src/external_requests/base_requests/external_request_with_body.py
src/external_requests/method_requests/__init__.py
src/external_requests/method_requests/delete_request.py
src/external_requests/method_requests/get_request.py
src/external_requests/method_requests/head_request.py
src/external_requests/method_requests/options_request.py
src/external_requests/method_requests/patch_request.py
src/external_requests/method_requests/post_request.py
src/external_requests/method_requests/put_request.py