Metadata-Version: 2.1
Name: external-requests
Version: 1.0.1
Home-page: https://gitlab.com/VenfiOranai/external-requests
Author: Venfi Oranai
Author-email: venfioranai@gmail.com
